BLE_led_ctrl/BLE_led_ctrl.srcs/sources_1/new/pwm.v
module pwm #(parameter W = 4)(
  input clk,
  input rst_n,
  input en,
  input [W-1:0] duty,
  output pwm_out
);

  reg [W-1:0] ctr_q;

  always @(posedge clk or negedge rst_n) begin
    if (!rst_n)
      ctr_q <= 0;
    else if (en)
      ctr_q <= ctr_q + 1'b1;
    else
      ctr_q <= 0;
  end
// duty == {W{1'b1}} forces full on; otherwise strictly les than 
  assign pwm_out = en && ((duty == {W{1'b1}})|| (ctr_q < duty));

endmodule

BLE_led_ctrl/BLE_led_ctrl.srcs/sources_1/new/output_control.v
module output_control (
  input clk,
  input rst_n,

  input led_enable,
  input use_ramp_brightness,

  input [2:0] cfg_color,
  input [3:0] cfg_brightness,
  input [3:0] ramp_brightness,

  output reg [2:0] led_out
);

  reg [3:0] duty_sel;
  wire pwm_sig;

  always @(*) begin
    if (use_ramp_brightness)
      duty_sel = ramp_brightness;
    else
      duty_sel = cfg_brightness;
  end

  pwm #(4) u_pwm (
    .clk(clk),
    .rst_n(rst_n),
    .en(led_enable),
    .duty(duty_sel),
    .pwm_out(pwm_sig)
  );

  always @(*) begin
    led_out[0] = pwm_sig & cfg_color[0];
    led_out[1] = pwm_sig & cfg_color[1];
    led_out[2] = pwm_sig & cfg_color[2];
  end

endmodule

BLE_led_ctrl/BLE_led_ctrl.srcs/sources_1/new/pattern_fsm.v


module pattern_fsm #(
  parameter BLINK_ON_TICKS     = 6'd20,
  parameter BLINK_OFF_TICKS    = 6'd20,
  parameter PULSE_ON_TICKS     = 6'd15,
  parameter PULSE_OFF_TICKS     = 6'd30,
  parameter BREATHE_STEP_TICKS = 6'd2
)(


  input clk,
  input rst_n,

  input [1:0] cfg_mode,
  input [3:0] cfg_brightness,
  input [5:0] cfg_time,

  input cmd_update_pulse,

  input phase_done,
  input duration_done,

  input [3:0] ramp_value,

  output reg phase_start,
  output reg [5:0] phase_load,

  output reg duration_start,
  output reg [5:0] duration_load,

  output reg ramp_clr,
  output reg ramp_step,
  output reg ramp_dir_up,

  output reg led_enable,
  output reg use_ramp_brightness,

  output pattern_active,
  output [2:0] state_dbg
);
  // Modes
localparam MODE_IDLE    = 2'b00;
localparam MODE_BLINK   = 2'b01;
localparam MODE_BREATHE = 2'b10;
localparam MODE_PULSE   = 2'b11;

// States
localparam S_IDLE      = 3'd0;
localparam S_ON        = 3'd1;
localparam S_OFF       = 3'd2;
localparam S_RAMP_UP   = 3'd3;
localparam S_RAMP_DOWN = 3'd4;
  reg [2:0] state_q, state_d;

  assign pattern_active = (state_q != S_IDLE);
  assign state_dbg = state_q;

  always @(*) begin
    state_d = state_q;

    phase_start = 0;
    phase_load  = 0;

    duration_start = 0;
    duration_load  = cfg_time;

    ramp_clr = 0;
    ramp_step = 0;
    ramp_dir_up = 1;

    led_enable = 0;
    use_ramp_brightness = 0;

    case (state_q)

      S_IDLE: begin
        ramp_clr = 1;

        if (cfg_mode == MODE_BLINK) begin
          state_d = S_ON;
          phase_start = 1;
          phase_load = BLINK_ON_TICKS;
          if (cfg_time != 0) duration_start = 1;
        end
        else if (cfg_mode == MODE_BREATHE) begin
          state_d = S_RAMP_UP;
          phase_start = 1;
          phase_load = BREATHE_STEP_TICKS;
          if (cfg_time != 0) duration_start = 1;
        end
        else if (cfg_mode == MODE_PULSE) begin
          state_d = S_ON;
          phase_start = 1;
          phase_load = PULSE_ON_TICKS;
          if (cfg_time != 0) duration_start = 1;
        end
      end

      S_ON: begin
        led_enable = 1;

        if (duration_done || cmd_update_pulse)
          state_d = S_IDLE;
        else if (phase_done) begin
          if (cfg_mode == MODE_BLINK) begin
            state_d = S_OFF;
            phase_start = 1;
            phase_load = BLINK_OFF_TICKS;
          end else if (cfg_mode == MODE_PULSE) begin
            state_d = S_OFF;
            phase_start = 1;
            phase_load = PULSE_OFF_TICKS;
            end else
              state_d = S_IDLE;
        end
      end

      S_OFF: begin
        if (duration_done || cmd_update_pulse)
          state_d = S_IDLE;
        else if (phase_done) begin
          if (cfg_mode == MODE_BLINK) begin
            state_d = S_ON;
            phase_start = 1;
            phase_load = BLINK_ON_TICKS;
          end else if (cfg_mode == MODE_PULSE) begin
            state_d = S_ON;
            phase_start = 1;
            phase_load = PULSE_ON_TICKS;
            end else
              state_d = S_IDLE;
        end
      end

      S_RAMP_UP: begin
        led_enable = 1;
        use_ramp_brightness = 1;

        if (duration_done || cmd_update_pulse)
          state_d = S_IDLE;
        else if (phase_done) begin
          ramp_step = 1;
          phase_start = 1;
          phase_load = BREATHE_STEP_TICKS;

          if ((ramp_value + 1) >= cfg_brightness)
            state_d = S_RAMP_DOWN;
        end
      end

      S_RAMP_DOWN: begin
        led_enable = 1;
        use_ramp_brightness = 1;
        ramp_dir_up = 0;

        if (duration_done || cmd_update_pulse)
          state_d = S_IDLE;
        else if (phase_done) begin
          ramp_step = 1;
          phase_start = 1;
          phase_load = BREATHE_STEP_TICKS;

          if (ramp_value <= 1)
            state_d = S_RAMP_UP;
        end
      end

      default: state_d = S_IDLE;

    endcase
  end

  always @(posedge clk or negedge rst_n) begin
    if (!rst_n)
      state_q <= S_IDLE;
    else
      state_q <= state_d;
  end

endmodule

BLE_led_ctrl/BLE_led_ctrl.srcs/sources_1/new/ramp_counter.v

module ramp_counter #(parameter W = 4)(
  input clk,
  input rst_n,
  input clr,
  input step,
  input dir_up,
  output reg [W-1:0] value_q
);

  always @(posedge clk or negedge rst_n) begin
    if (!rst_n)
      value_q <= 0;
    else if (clr)
      value_q <= 0;
    else if (step) begin
      if (dir_up) begin
        if (value_q != {W{1'b1}})
          value_q <= value_q + 1'b1;
      end else begin
        if (value_q != 0)
          value_q <= value_q - 1'b1;
      end
    end
  end

endmodule

BLE_led_ctrl/BLE_led_ctrl.srcs/sources_1/new/timer_down.v
module timer_down #(parameter W = 6)(
  input clk,
  input rst_n,
  input start,
  input [W-1:0] load_val,
  output reg running,
  output reg done_pulse,
  output reg [W-1:0] count_q
);

  always @(posedge clk or negedge rst_n) begin
    if (!rst_n) begin
      count_q    <= {W{1'b0}};
      running    <= 1'b0;
      done_pulse <= 1'b0;
    end else begin
      done_pulse <= 1'b0;

      if (start) begin
        if (load_val != 0) begin
          count_q <= load_val;
          running <= 1'b1;
        end else begin
          count_q <= 0;
          running <= 1'b0;
        end
      end else if (running) begin
        if (count_q == 1) begin
          count_q    <= 0;
          running    <= 1'b0;
          done_pulse <= 1'b1;
        end else begin
          count_q <= count_q - 1'b1;
        end
      end
    end
  end

endmodule

BLE_led_ctrl/BLE_led_ctrl.srcs/sources_1/new/reg_file.v
`timescale 1ns / 1ps
//////////////////////////////////////////////////////////////////////////////////
// Company: 
// Engineer: 
// 
// Create Date: 19.04.2026 17:10:31
// Design Name: 
// Module Name: reg_file
// Project Name: 
// Target Devices: 
// Tool Versions: 
// Description: 
// 
// Dependencies: 
// 
// Revision:
// Revision 0.01 - File Created
// Additional Comments:
// 
//////////////////////////////////////////////////////////////////////////////////


module reg_file (
  input clk,
  input rst_n,

  input wr_en,
  input [1:0] wr_mode,
  input [2:0] wr_color,
  input [3:0] wr_brightness,
  input [5:0] wr_time,

  output reg [1:0] cfg_mode,
  output reg [2:0] cfg_color,
  output reg [3:0] cfg_brightness,
  output reg [5:0] cfg_time,

  input sts_active_in,
  input [2:0] sts_state_in,

  output reg sts_active,
  output reg [2:0] sts_state
);

  always @(posedge clk or negedge rst_n) begin
    if (!rst_n) begin
      cfg_mode       <= 2'b00;
      cfg_color      <= 3'b000;
      cfg_brightness <= 4'hF;
      cfg_time       <= 6'd0;

      sts_active     <= 1'b0;
      sts_state      <= 3'd0;
    end else begin
      if (wr_en) begin
        cfg_mode       <= wr_mode;
        cfg_color      <= wr_color;
        cfg_brightness <= wr_brightness;
        cfg_time       <= wr_time;
      end

      sts_active <= sts_active_in;
      sts_state  <= sts_state_in;
    end
  end

endmodule

BLE_led_ctrl/BLE_led_ctrl.srcs/sources_1/new/decoder.v
module decoder (
  input [15:0] pkt,

  output reg [1:0] mode,
  output reg [2:0] color,
  output reg [3:0] brightness,
  output reg [5:0] time_val
);

  always @(*) begin
    mode       = pkt[15:14];
    color      = pkt[12:10];
    brightness = pkt[9:6];
    time_val   = pkt[5:0];
  end

endmodule

BLE_led_ctrl/BLE_led_ctrl.srcs/sources_1/new/cmd_interface.v
module cmd_interface #(parameter W = 16)(
  input clk,
  input rst_n,

  input in_valid,
  output in_ready,
  input [W-1:0] in_data,

  output out_valid,
  input out_ready,
  output [W-1:0] out_data
);

  reg full;
  reg [W-1:0] buf_q;

  assign out_valid = full;
  assign out_data  = buf_q;
  assign in_ready  = ~full || (out_valid && out_ready);

  always @(posedge clk or negedge rst_n) begin
    if (!rst_n) begin
      full  <= 1'b0;
      buf_q <= {W{1'b0}};
    end else begin
      if (out_valid && out_ready)
        full <= 1'b0;

      if (in_valid && in_ready) begin
        buf_q <= in_data;
        full  <= 1'b1;
      end
    end
  end

endmodule

BLE_led_ctrl/BLE_led_ctrl.srcs/sources_1/new/led_ctrl_top.v


module led_ctrl_top (
  input clk,
  input rst_n,

  // Bluetooth-stack-facing side
  input stack_valid,
  output stack_ready,
  input [15:0] stack_data,

  // LED outputs
  output [2:0] led_out
);

  // ------------------------------------------------------------
  // Command Interface
  // ------------------------------------------------------------
  wire        cmd_valid;
  wire        cmd_ready;
  wire [15:0] cmd_data;
  

  cmd_interface #(16) u_cmd_if (
    .clk      (clk),
    .rst_n    (rst_n),
    .in_valid (stack_valid),
    .in_ready (stack_ready),
    .in_data  (stack_data),
    .out_valid(cmd_valid),
    .out_ready(cmd_ready),
    .out_data (cmd_data)
  );
// Mapping switches to stack_data while tying Bit 13 and Bits 12:10 to Zero
  assign cmd_ready = 1'b1; // always consume

  // ------------------------------------------------------------
  // Decoder
  // ------------------------------------------------------------
  wire [1:0] dec_mode;
  wire [2:0] dec_color;
  wire [3:0] dec_brightness;
  wire [5:0] dec_time;

  decoder u_dec (
    .pkt       (cmd_data),
    .mode      (dec_mode),
    .color     (dec_color),
    .brightness(dec_brightness),
    .time_val  (dec_time)
  );

  wire reg_wr_en;
  assign reg_wr_en = cmd_valid & cmd_ready;

  // ------------------------------------------------------------
  // Register File
  // ------------------------------------------------------------
  wire [1:0] cfg_mode;
  wire [2:0] cfg_color;
  wire [3:0] cfg_brightness;
  wire [5:0] cfg_time;

  wire       sts_active;
  wire [2:0] sts_state;

  reg_file u_regs (
    .clk           (clk),
    .rst_n         (rst_n),
    .wr_en         (reg_wr_en),
    .wr_mode       (dec_mode),
    .wr_color      (dec_color),
    .wr_brightness (dec_brightness),
    .wr_time       (dec_time),
    .cfg_mode      (cfg_mode),
    .cfg_color     (cfg_color),
    .cfg_brightness(cfg_brightness),
    .cfg_time      (cfg_time),
    .sts_active_in (sts_active),
    .sts_state_in  (sts_state),
    .sts_active    (),
    .sts_state     ()
  );

  // ------------------------------------------------------------
  // Phase Timer
  // ------------------------------------------------------------
  wire       phase_start;
  wire [5:0] phase_load;
  wire       phase_running;
  wire       phase_done;
  wire [5:0] phase_count;

  timer_down #(6) u_phase_timer (
    .clk       (clk),
    .rst_n     (rst_n),
    .start     (phase_start),
    .load_val  (phase_load),
    .running   (phase_running),
    .done_pulse(phase_done),
    .count_q   (phase_count)
  );

  // ------------------------------------------------------------
  // Duration Timer
  // ------------------------------------------------------------
  wire       duration_start;
  wire [5:0] duration_load;
  wire       duration_running;
  wire       duration_done;
  wire [5:0] duration_count;

  timer_down #(6) u_duration_timer (
    .clk       (clk),
    .rst_n     (rst_n),
    .start     (duration_start),
    .load_val  (duration_load),
    .running   (duration_running),
    .done_pulse(duration_done),
    .count_q   (duration_count)
  );

  // ------------------------------------------------------------
  // Ramp Counter
  // ------------------------------------------------------------
  wire       ramp_clr;
  wire       ramp_step;
  wire       ramp_dir_up;
  wire [3:0] ramp_value;

  ramp_counter #(4) u_ramp (
    .clk    (clk),
    .rst_n  (rst_n),
    .clr    (ramp_clr),
    .step   (ramp_step),
    .dir_up (ramp_dir_up),
    .value_q(ramp_value)
  );

  // ------------------------------------------------------------
  // Pattern FSM
  // ------------------------------------------------------------
  wire led_enable;
  wire use_ramp_brightness;
  wire pattern_active;
  wire [2:0] state_dbg;

  pattern_fsm u_fsm (
    .clk                 (clk),
    .rst_n               (rst_n),
    .cfg_mode            (cfg_mode),
    .cfg_brightness      (cfg_brightness),
    .cfg_time            (cfg_time),
    .cmd_update_pulse    (reg_wr_en),
    .phase_done          (phase_done),
    .duration_done       (duration_done),
    .ramp_value          (ramp_value),
    .phase_start         (phase_start),
    .phase_load          (phase_load),
    .duration_start      (duration_start),
    .duration_load       (duration_load),
    .ramp_clr            (ramp_clr),
    .ramp_step           (ramp_step),
    .ramp_dir_up         (ramp_dir_up),
    .led_enable          (led_enable),
    .use_ramp_brightness (use_ramp_brightness),
    .pattern_active      (pattern_active),
    .state_dbg           (state_dbg)
  );

  assign sts_active = pattern_active;
  assign sts_state  = state_dbg;

  // ------------------------------------------------------------
  // Output Control
  // ------------------------------------------------------------
  output_control u_out (
    .clk                (clk),
    .rst_n              (rst_n),
    .led_enable         (led_enable),
    .use_ramp_brightness(use_ramp_brightness),
    .cfg_color          (cfg_color),
    .cfg_brightness     (cfg_brightness),
    .ramp_brightness    (ramp_value),
    .led_out            (led_out)
  );

endmodule

BLE_led_ctrl/BLE_led_ctrl.srcs/sim_1/new/tb_led_ctrl.v
`timescale 1ns/1ps
//`default_nettype none

module tb_led_ctrl_top;

  // ------------------------------------------------------------
  // DUT Signals
  // ------------------------------------------------------------
  reg clk;
  reg rst_n;

  reg        stack_valid;
  wire       stack_ready;
  reg [15:0] stack_data;

  wire [2:0] led_out;

  // ------------------------------------------------------------
  // Instantiate DUT
  // ------------------------------------------------------------
  led_ctrl_top dut (
    .clk         (clk),
    .rst_n       (rst_n),
    .stack_valid (stack_valid),
    .stack_ready (stack_ready),
    .stack_data  (stack_data),
    .led_out     (led_out)
  );

  // ------------------------------------------------------------
  // Clock: 100 MHz
  // ------------------------------------------------------------
  initial clk = 1'b0;
  always #5 clk = ~clk;

  // ------------------------------------------------------------
  // Packet builder
  // ------------------------------------------------------------
  function [15:0] build_pkt;
    input [1:0] mode;
    input [2:0] color;
    input [3:0] brightness;
    input [5:0] duration;
    begin
      build_pkt = {mode, 1'b0, color, brightness, duration};
    end
  endfunction

  // ------------------------------------------------------------
  // Send command (1-cycle valid pulse)
  // ------------------------------------------------------------
  task send_cmd;
    input [15:0] pkt;
    begin
      @(posedge clk);
      stack_data  <= pkt;
      stack_valid <= 1'b1;

      @(posedge clk);
      stack_valid <= 1'b0;
    end
  endtask

  // ------------------------------------------------------------
  // Dump waves
  // ------------------------------------------------------------
  initial begin
    $dumpfile("led_ctrl.vcd");
    $dumpvars(0, tb_led_ctrl_top);
  end

  // ------------------------------------------------------------
  // Test sequence
  // ------------------------------------------------------------
  initial begin
    // Init
    stack_valid = 0;
    stack_data  = 0;
    rst_n       = 0;

    // Reset
    repeat (5) @(posedge clk);
    rst_n = 1;

    // ==========================================================
    // 1. BLINK MODE
    // ==========================================================
    $display("\n--- BLINK MODE ---");
    send_cmd(build_pkt(2'b01, 3'b111, 4'd10, 6'd40));

    // Let blink run long enough
    repeat (200) @(posedge clk);

    // ==========================================================
    // 2. PULSE MODE
    // ==========================================================
    $display("\n--- PULSE MODE ---");
    send_cmd(build_pkt(2'b11, 3'b001, 4'd12, 6'd40));

    // Observe pulse clearly
    repeat (150) @(posedge clk);

    // ==========================================================
    // 3. BREATHE MODE (2 FULL CYCLES)
    // ==========================================================
    $display("\n--- BREATHE MODE ---");
    send_cmd(build_pkt(2'b10, 3'b010, 4'd12, 6'd120));

    // Long run → ensures full ramp up/down cycles
    repeat (600) @(posedge clk);

    // ==========================================================
    // 4. CORNER CASE: MID-RUN UPDATE
    // ==========================================================
    $display("\n--- CORNER CASE: MID-RUN UPDATE ---");

    // Start blink
    send_cmd(build_pkt(2'b01, 3'b111, 4'd10, 6'd60));
    repeat (80) @(posedge clk);

    // Interrupt with breathe
    send_cmd(build_pkt(2'b10, 3'b011, 4'd12, 6'd100));

    // Observe transition behavior
    repeat (400) @(posedge clk);

    // ==========================================================
    // DONE
    // ==========================================================
    $display("\nALL TESTS COMPLETED");
    $finish;
  end

endmodule

//`default_nettype wire

BLE_led_ctrl/BLE_led_ctrl.sim/sim_1/behav/xsim/led_ctrl.vcd
$date
   Tue Apr 21 22:46:53 2026
$end

$version
  2024.2.0
  $dumpfile ("led_ctrl.vcd") 
$end

$timescale
  1ps
$end

$scope module tb_led_ctrl_top $end
$var reg 1 ! clk $end
$var reg 1 " rst_n $end
$var reg 1 # stack_valid $end
$var wire 1 $ stack_ready $end
$var reg 16 % stack_data [15:0] $end
$var wire 3 & led_out [2:0] $end
$scope module dut $end
$var wire 1 ' clk $end
$var wire 1 ( rst_n $end
$var wire 1 ) stack_valid $end
$var wire 1 $ stack_ready $end
$var wire 16 * stack_data [15:0] $end
$var wire 3 & led_out [2:0] $end
$var wire 1 + cmd_valid $end
$var wire 1 , cmd_ready $end
$var wire 16 - cmd_data [15:0] $end
$var wire 2 . dec_mode [1:0] $end
$var wire 3 / dec_color [2:0] $end
$var wire 4 0 dec_brightness [3:0] $end
$var wire 6 1 dec_time [5:0] $end
$var wire 1 2 reg_wr_en $end
$var wire 2 3 cfg_mode [1:0] $end
$var wire 3 4 cfg_color [2:0] $end
$var wire 4 5 cfg_brightness [3:0] $end
$var wire 6 6 cfg_time [5:0] $end
$var wire 1 7 sts_active $end
$var wire 3 8 sts_state [2:0] $end
$var wire 1 9 phase_start $end
$var wire 6 : phase_load [5:0] $end
$var wire 1 ; phase_running $end
$var wire 1 < phase_done $end
$var wire 6 = phase_count [5:0] $end
$var wire 1 > duration_start $end
$var wire 6 ? duration_load [5:0] $end
$var wire 1 @ duration_running $end
$var wire 1 A duration_done $end
$var wire 6 B duration_count [5:0] $end
$var wire 1 C ramp_clr $end
$var wire 1 D ramp_step $end
$var wire 1 E ramp_dir_up $end
$var wire 4 F ramp_value [3:0] $end
$var wire 1 G led_enable $end
$var wire 1 H use_ramp_brightness $end
$var wire 1 I pattern_active $end
$var wire 3 J state_dbg [2:0] $end
$scope module u_cmd_if $end
$var wire 1 ' clk $end
$var wire 1 ( rst_n $end
$var wire 1 ) in_valid $end
$var wire 1 $ in_ready $end
$var wire 16 * in_data [15:0] $end
$var wire 1 + out_valid $end
$var wire 1 , out_ready $end
$var wire 16 - out_data [15:0] $end
$var reg 1 K full $end
$var reg 16 L buf_q [15:0] $end
$upscope $end
$scope module u_dec $end
$var wire 16 - pkt [15:0] $end
$var reg 2 M mode [1:0] $end
$var reg 3 N color [2:0] $end
$var reg 4 O brightness [3:0] $end
$var reg 6 P time_val [5:0] $end
$upscope $end
$scope module u_regs $end
$var wire 1 ' clk $end
$var wire 1 ( rst_n $end
$var wire 1 2 wr_en $end
$var wire 2 . wr_mode [1:0] $end
$var wire 3 / wr_color [2:0] $end
$var wire 4 0 wr_brightness [3:0] $end
$var wire 6 1 wr_time [5:0] $end
$var reg 2 Q cfg_mode [1:0] $end
$var reg 3 R cfg_color [2:0] $end
$var reg 4 S cfg_brightness [3:0] $end
$var reg 6 T cfg_time [5:0] $end
$var wire 1 7 sts_active_in $end
$var wire 3 8 sts_state_in [2:0] $end
$var reg 1 U sts_active $end
$var reg 3 V sts_state [2:0] $end
$upscope $end
$scope module u_phase_timer $end
$var wire 1 ' clk $end
$var wire 1 ( rst_n $end
$var wire 1 9 start $end
$var wire 6 : load_val [5:0] $end
$var reg 1 W running $end
$var reg 1 X done_pulse $end
$var reg 6 Y count_q [5:0] $end
$upscope $end
$scope module u_duration_timer $end
$var wire 1 ' clk $end
$var wire 1 ( rst_n $end
$var wire 1 > start $end
$var wire 6 ? load_val [5:0] $end
$var reg 1 Z running $end
$var reg 1 [ done_pulse $end
$var reg 6 \ count_q [5:0] $end
$upscope $end
$scope module u_ramp $end
$var wire 1 ' clk $end
$var wire 1 ( rst_n $end
$var wire 1 C clr $end
$var wire 1 D step $end
$var wire 1 E dir_up $end
$var reg 4 ] value_q [3:0] $end
$upscope $end
$scope module u_fsm $end
$var wire 1 ' clk $end
$var wire 1 ( rst_n $end
$var wire 2 3 cfg_mode [1:0] $end
$var wire 4 5 cfg_brightness [3:0] $end
$var wire 6 6 cfg_time [5:0] $end
$var wire 1 2 cmd_update_pulse $end
$var wire 1 < phase_done $end
$var wire 1 A duration_done $end
$var wire 4 F ramp_value [3:0] $end
$var reg 1 ^ phase_start $end
$var reg 6 _ phase_load [5:0] $end
$var reg 1 ` duration_start $end
$var reg 6 a duration_load [5:0] $end
$var reg 1 b ramp_clr $end
$var reg 1 c ramp_step $end
$var reg 1 d ramp_dir_up $end
$var reg 1 e led_enable $end
$var reg 1 f use_ramp_brightness $end
$var wire 1 I pattern_active $end
$var wire 3 J state_dbg [2:0] $end
$var reg 3 g state_q [2:0] $end
$var reg 3 h state_d [2:0] $end
$upscope $end
$scope module u_out $end
$var wire 1 ' clk $end
$var wire 1 ( rst_n $end
$var wire 1 G led_enable $end
$var wire 1 H use_ramp_brightness $end
$var wire 3 4 cfg_color [2:0] $end
$var wire 4 5 cfg_brightness [3:0] $end
$var wire 4 F ramp_brightness [3:0] $end
$var reg 3 i led_out [2:0] $end
$var reg 4 j duty_sel [3:0] $end
$var wire 1 k pwm_sig $end
$scope module u_pwm $end
$var wire 1 ' clk $end
$var wire 1 ( rst_n $end
$var wire 1 G en $end
$var wire 4 l duty [3:0] $end
$var wire 1 k pwm_out $end
$var reg 4 m ctr_q [3:0] $end
$upscope $end
$upscope $end
$upscope $end
$scope function build_pkt $end
$var reg 16 n build_pkt [15:0] $end
$var reg 2 o mode [1:0] $end
$var reg 3 p color [2:0] $end
$var reg 4 q brightness [3:0] $end
$var reg 6 r duration [5:0] $end
$upscope $end
$scope task send_cmd $end
$var reg 16 s pkt [15:0] $end
$upscope $end
$upscope $end
$enddefinitions $end

#0
$dumpvars
0!
0"
0#
1$
b0 %
b0 &
0'
0(
0)
b0 *
0+
1,
b0 -
b0 .
b0 /
b0 0
b0 1
02
b0 3
b0 4
b1111 5
b0 6
07
b0 8
09
b0 :
0;
0<
b0 =
0>
b0 ?
0@
0A
b0 B
1C
0D
1E
b0 F
0G
0H
0I
b0 J
0K
b0 L
b0 M
b0 N
b0 O
b0 P
b0 Q
b0 R
b1111 S
b0 T
0U
b0 V
0W
0X
b0 Y
0Z
0[
b0 \
b0 ]
0^
b0 _
0`
b0 a
1b
0c
1d
0e
0f
b0 g
b0 h
b0 i
b1111 j
0k
b1111 l
b0 m
bx n
bx o
bx p
bx q
bx r
bx s
$end

#5000
1!
1'

#10000
0!
0'

#15000
1!
1'

#20000
0!
0'

#25000
1!
1'

#30000
0!
0'

#35000
1!
1'

#40000
0!
0'

#45000
1!
1"
1'
1(
b101111010101000 n
b1 o
b111 p
b1010 q
b101000 r
b101111010101000 s

#50000
0!
0'

#55000
1!
1#
b101111010101000 %
1'
1)
b101111010101000 *

#60000
0!
0'

#65000
1!
0#
1'
0)
1+
b101111010101000 -
b1 .
b111 /
b1010 0
b101000 1
12
1K
b101111010101000 L
b1 M
b111 N
b1010 O
b101000 P
1b

#70000
0!
0'

#75000
1!
1'
0+
02
b1 3
b111 4
b1010 5
b101000 6
19
b10100 :
1>
b101000 ?
0K
b1 Q
b111 R
b1010 S
b101000 T
1^
b10100 _
1`
b101000 a
1b
b1 h
b1010 j
b1010 l

#80000
0!
0'

#85000
1!
b111 &
1'
17
b1 8
09
b0 :
1;
b10100 =
0>
1@
b101000 B
0C
1G
1I
b1 J
1W
b10100 Y
1Z
b101000 \
0^
b0 _
0`
0b
1e
b1 g
b111 i
1k

#90000
0!
0'

#95000
1!
1'
b10011 =
b100111 B
1U
b1 V
b10011 Y
b100111 \
b1 m

#100000
0!
0'

#105000
1!
1'
b10010 =
b100110 B
b10010 Y
b100110 \
b10 m

#110000
0!
0'

#115000
1!
1'
b10001 =
b100101 B
b10001 Y
b100101 \
b11 m

#120000
0!
0'

#125000
1!
1'
b10000 =
b100100 B
b10000 Y
b100100 \
b100 m

#130000
0!
0'

#135000
1!
1'
b1111 =
b100011 B
b1111 Y
b100011 \
b101 m

#140000
0!
0'

#145000
1!
1'
b1110 =
b100010 B
b1110 Y
b100010 \
b110 m

#150000
0!
0'

#155000
1!
1'
b1101 =
b100001 B
b1101 Y
b100001 \
b111 m

#160000
0!
0'

#165000
1!
1'
b1100 =
b100000 B
b1100 Y
b100000 \
b1000 m

#170000
0!
0'

#175000
1!
1'
b1011 =
b11111 B
b1011 Y
b11111 \
b1001 m

#180000
0!
0'

#185000
1!
b0 &
1'
b1010 =
b11110 B
b1010 Y
b11110 \
b0 i
0k
b1010 m

#190000
0!
0'

#195000
1!
1'
b1001 =
b11101 B
b1001 Y
b11101 \
b1011 m

#200000
0!
0'

#205000
1!
1'
b1000 =
b11100 B
b1000 Y
b11100 \
b1100 m

#210000
0!
0'

#215000
1!
1'
b111 =
b11011 B
b111 Y
b11011 \
b1101 m

#220000
0!
0'

#225000
1!
1'
b110 =
b11010 B
b110 Y
b11010 \
b1110 m

#230000
0!
0'

#235000
1!
1'
b101 =
b11001 B
b101 Y
b11001 \
b1111 m

#240000
0!
0'

#245000
1!
b111 &
1'
b100 =
b11000 B
b100 Y
b11000 \
b111 i
1k
b0 m

#250000
0!
0'

#255000
1!
1'
b11 =
b10111 B
b11 Y
b10111 \
b1 m

#260000
0!
0'

#265000
1!
1'
b10 =
b10110 B
b10 Y
b10110 \
b10 m

#270000
0!
0'

#275000
1!
1'
b1 =
b10101 B
b1 Y
b10101 \
b11 m

#280000
0!
0'

#285000
1!
1'
19
b10100 :
0;
1<
b0 =
b10100 B
0W
1X
b0 Y
b10100 \
1^
b10100 _
1e
b10 h
b100 m

#290000
0!
0'

#295000
1!
b0 &
1'
b10 8
09
b0 :
1;
0<
b10100 =
b10011 B
0G
b10 J
1W
0X
b10100 Y
b10011 \
0^
b0 _
0e
b10 g
b0 i
0k
b101 m

#300000
0!
0'

#305000
1!
1'
b10011 =
b10010 B
b10 V
b10011 Y
b10010 \
b0 m

#310000
0!
0'

#315000
1!
1'
b10010 =
b10001 B
b10010 Y
b10001 \

#320000
0!
0'

#325000
1!
1'
b10001 =
b10000 B
b10001 Y
b10000 \

#330000
0!
0'

#335000
1!
1'
b10000 =
b1111 B
b10000 Y
b1111 \

#340000
0!
0'

#345000
1!
1'
b1111 =
b1110 B
b1111 Y
b1110 \

#350000
0!
0'

#355000
1!
1'
b1110 =
b1101 B
b1110 Y
b1101 \

#360000
0!
0'

#365000
1!
1'
b1101 =
b1100 B
b1101 Y
b1100 \

#370000
0!
0'

#375000
1!
1'
b1100 =
b1011 B
b1100 Y
b1011 \

#380000
0!
0'

#385000
1!
1'
b1011 =
b1010 B
b1011 Y
b1010 \

#390000
0!
0'

#395000
1!
1'
b1010 =
b1001 B
b1010 Y
b1001 \

#400000
0!
0'

#405000
1!
1'
b1001 =
b1000 B
b1001 Y
b1000 \

#410000
0!
0'

#415000
1!
1'
b1000 =
b111 B
b1000 Y
b111 \

#420000
0!
0'

#425000
1!
1'
b111 =
b110 B
b111 Y
b110 \

#430000
0!
0'

#435000
1!
1'
b110 =
b101 B
b110 Y
b101 \

#440000
0!
0'

#445000
1!
1'
b101 =
b100 B
b101 Y
b100 \

#450000
0!
0'

#455000
1!
1'
b100 =
b11 B
b100 Y
b11 \

#460000
0!
0'

#465000
1!
1'
b11 =
b10 B
b11 Y
b10 \

#470000
0!
0'

#475000
1!
1'
b10 =
b1 B
b10 Y
b1 \

#480000
0!
0'

#485000
1!
1'
b1 =
0@
1A
b0 B
b1 Y
0Z
1[
b0 \
b0 h

#490000
0!
0'

#495000
1!
1'
07
b0 8
19
b10100 :
0;
1<
b0 =
1>
0A
1C
0I
b0 J
0W
1X
b0 Y
0[
1^
b10100 _
1`
1b
b0 g
b1 h

#500000
0!
0'

#505000
1!
b111 &
1'
17
b1 8
09
b0 :
1;
0<
b10100 =
0>
1@
b101000 B
0C
1G
1I
b1 J
0U
b0 V
1W
0X
b10100 Y
1Z
b101000 \
0^
b0 _
0`
0b
1e
b1 g
b111 i
1k

#510000
0!
0'

#515000
1!
1'
b10011 =
b100111 B
1U
b1 V
b10011 Y
b100111 \
b1 m

#520000
0!
0'

#525000
1!
1'
b10010 =
b100110 B
b10010 Y
b100110 \
b10 m

#530000
0!
0'

#535000
1!
1'
b10001 =
b100101 B
b10001 Y
b100101 \
b11 m

#540000
0!
0'

#545000
1!
1'
b10000 =
b100100 B
b10000 Y
b100100 \
b100 m

#550000
0!
0'

#555000
1!
1'
b1111 =
b100011 B
b1111 Y
b100011 \
b101 m

#560000
0!
0'

#565000
1!
1'
b1110 =
b100010 B
b1110 Y
b100010 \
b110 m

#570000
0!
0'

#575000
1!
1'
b1101 =
b100001 B
b1101 Y
b100001 \
b111 m

#580000
0!
0'

#585000
1!
1'
b1100 =
b100000 B
b1100 Y
b100000 \
b1000 m

#590000
0!
0'

#595000
1!
1'
b1011 =
b11111 B
b1011 Y
b11111 \
b1001 m

#600000
0!
0'

#605000
1!
b0 &
1'
b1010 =
b11110 B
b1010 Y
b11110 \
b0 i
0k
b1010 m

#610000
0!
0'

#615000
1!
1'
b1001 =
b11101 B
b1001 Y
b11101 \
b1011 m

#620000
0!
0'

#625000
1!
1'
b1000 =
b11100 B
b1000 Y
b11100 \
b1100 m

#630000
0!
0'

#635000
1!
1'
b111 =
b11011 B
b111 Y
b11011 \
b1101 m

#640000
0!
0'

#645000
1!
1'
b110 =
b11010 B
b110 Y
b11010 \
b1110 m

#650000
0!
0'

